libfreeiot/__init__.py
libfreeiot/app.py
libfreeiot/config.py
libfreeiot/version.py
libfreeiot/adapters/__init__.py
libfreeiot/adapters/base.py
libfreeiot/adapters/file/__init__.py
libfreeiot/adapters/file/main.py
libfreeiot/adapters/mqtt/__init__.py
libfreeiot/adapters/mqtt/main.py
libfreeiot/adapters/mqtt/Constant/Status.py
libfreeiot/adapters/mqtt/Constant/__init__.py
libfreeiot/adapters/mqtt/Parse/__init__.py
libfreeiot/adapters/mqtt/Parse/main.py
libfreeiot/adapters/mqtt/Parse/sys.py
libfreeiot/core/__init__.py
libfreeiot/core/routes.py
libfreeiot/core/resources/__init__.py
libfreeiot/core/resources/data.py
libfreeiot/core/resources/device.py
libfreeiot-0.9.18.dist-info/METADATA
libfreeiot-0.9.18.dist-info/RECORD
libfreeiot-0.9.18.dist-info/WHEEL
libfreeiot-0.9.18.dist-info/top_level.txt
