Metadata-Version: 2.1
Name: libfreeiot
Version: 0.9.18
Summary: A free, open-source IoT Framework
Home-page: https://github.com/noahziheng/freeiot
Author: Noah Gao
Author-email: noahgaocn@outlook.com
License: UNKNOWN
Download-URL: https://github.com/noahziheng/freeiot/archive/0.9.18.tar.gz
Platform: UNKNOWN
Requires-Dist: Flask (>=0.12.2)
Requires-Dist: Flask-JWT-Simple (>=0.0.3)
Requires-Dist: Flask-PyMongo (>=0.5.1)
Requires-Dist: Flask-RESTful (>=0.3.6)
Requires-Dist: paho-mqtt (>=1.3.1)
Requires-Dist: pylint (>=1.8.2)
Requires-Dist: python-dotenv (>=0.7.1)
